{
  "id": "stylesheets/create-a-page",
  "title": "Collect Page",
  "description": "Styles elements found directly on the Collect page",
  "source": "@site/docs/stylesheets/create-a-page.md",
  "sourceDirName": "stylesheets",
  "slug": "/stylesheets/create-a-page",
  "permalink": "/docs/stylesheets/create-a-page",
  "draft": false,
  "unlisted": false,
  "editUrl": "https://github.com/facebook/docusaurus/tree/main/packages/create-docusaurus/templates/shared/docs/stylesheets/create-a-page.md",
  "tags": [],
  "version": "current",
  "sidebarPosition": 1,
  "frontMatter": {
    "sidebar_position": 1
  },
  "sidebar": "styleSidebar",
  "previous": {
    "title": "StyleSheets",
    "permalink": "/docs/category/stylesheets"
  }
}